formforge/__init__.py
formforge-0.0.0.dist-info/WHEEL
formforge-0.0.0.dist-info/METADATA
formforge-0.0.0.dist-info/RECORD
