Metadata-Version: 2.3
Name: formforge
Version: 0.0.0
Summary: Dataclasses with coercion, and structured input format exports
Author: Thomas Lovén
Author-email: Thomas Lovén <formforge@thomasloven.com>
Classifier: Programming Language :: Python :: 3
Classifier: Operating System :: OS Independent
Requires-Python: >=3.12
Project-URL: Homepage, https://github.com/thomasloven/formforge
